lukis/GenTestCode.py
lukis/__init__.py
lukis/command.py
lukis/lukis.py
lukis/makepdf.py
lukis/myfont.py
lukis/myimage.py
lukis/mypretty.py
lukis/plot.py
lukis/symbol.py
lukis-0.18.5.dist-info/METADATA
lukis-0.18.5.dist-info/RECORD
lukis-0.18.5.dist-info/WHEEL
lukis-0.18.5.dist-info/top_level.txt
