Metadata-Version: 2.1
Name: lukis
Version: 0.18.5
Summary: Generate a device independent vector graphic stream that can be converted to pdf, svg, or other vector graphic format.
Home-page: UNKNOWN
Author: CHEN, Lee Chuin
Author-email: leechuin@gmail.com
License: MIT
Keywords: lukis vector graphic pdf svg
Platform: UNKNOWN
Classifier: Development Status :: 3 - Alpha
Classifier: Intended Audience :: Education
Classifier: Topic :: Scientific/Engineering :: Visualization
Classifier: License :: OSI Approved :: MIT License
Classifier: Programming Language :: Python :: 3
Classifier: Programming Language :: Python :: 3.3
Classifier: Programming Language :: Python :: 3.4
Classifier: Programming Language :: Python :: 3.5
Requires-Python: >=3
Requires-Dist: numpy
Requires-Dist: pillow
